{
  "success": true,
  "data": [
    {
      "id": 134718,
      "school_id": 353,
      "code": "7310101",
      "display_code": null,
      "name": "Kinh tế",
      "block": "A00;A01;D01;D90",
      "mark": 24.5,
      "quota": null,
      "type": 1,
      "mark_type": 1,
      "year": 2023,
      "introtext": "",
      "created_at": "2025-01-01T00:28:01.000Z",
      "updated_at": "2025-01-01T00:28:01.000Z",
      "published_at": null,
      "create_by": "cucnt",
      "status_mark": 1,
      "block_code": null,
      "school_code": null,
      "formula": null,
      "active": null,
      "updated_by": null,
      "admission_name": "Điểm thi THPT",
      "admission_alias": "diem-thi-thpt"
    },
    {
      "id": 134719,
      "school_id": 353,
      "code": "7310107",
      "display_code": null,
      "name": "Thông kê kinh tế",
      "block": "A00;A01;D01;D90",
      "mark": 23.5,
      "quota": null,
      "type": 1,
      "mark_type": 1,
      "year": 2023,
      "introtext": "",
      "created_at": "2025-01-01T00:28:01.000Z",
      "updated_at": "2025-01-01T00:28:01.000Z",
      "published_at": null,
      "create_by": "cucnt",
      "status_mark": 1,
      "block_code": null,
      "school_code": null,
      "formula": null,
      "active": null,
      "updated_by": null,
      "admission_name": "Điểm thi THPT",
      "admission_alias": "diem-thi-thpt"
    },
    {
      "id": 134720,
      "school_id": 353,
      "code": "7310205",
      "display_code": null,
      "name": "Quản lý nhà nước",
      "block": "A00;A01;D01;D96",
      "mark": 23,
      "quota": null,
      "type": 1,
      "mark_type": 1,
      "year": 2023,
      "introtext": "",
      "created_at": "2025-01-01T00:28:01.000Z",
      "updated_at": "2025-01-01T00:28:01.000Z",
      "published_at": null,
      "create_by": "cucnt",
      "status_mark": 1,
      "block_code": null,
      "school_code": null,
      "formula": null,
      "active": null,
      "updated_by": null,
      "admission_name": "Điểm thi THPT",
      "admission_alias": "diem-thi-thpt"
    },
    {
      "id": 134721,
      "school_id": 353,
      "code": "7340101",
      "display_code": null,
      "name": "Quản  trị kinh doanh",
      "block": "A00;A01;D01;D90",
      "mark": 24.75,
      "quota": null,
      "type": 1,
      "mark_type": 1,
      "year": 2023,
      "introtext": "",
      "created_at": "2025-01-01T00:28:01.000Z",
      "updated_at": "2025-01-01T00:28:01.000Z",
      "published_at": null,
      "create_by": "cucnt",
      "status_mark": 1,
      "block_code": null,
      "school_code": null,
      "formula": null,
      "active": null,
      "updated_by": null,
      "admission_name": "Điểm thi THPT",
      "admission_alias": "diem-thi-thpt"
    },
    {
      "id": 134722,
      "school_id": 353,
      "code": "7340115",
      "display_code": null,
      "name": "Marketing",
      "block": "A00;A01;D01;D90",
      "mark": 25.75,
      "quota": null,
      "type": 1,
      "mark_type": 1,
      "year": 2023,
      "introtext": "",
      "created_at": "2025-01-01T00:28:01.000Z",
      "updated_at": "2025-01-01T00:28:01.000Z",
      "published_at": null,
      "create_by": "cucnt",
      "status_mark": 1,
      "block_code": null,
      "school_code": null,
      "formula": null,
      "active": null,
      "updated_by": null,
      "admission_name": "Điểm thi THPT",
      "admission_alias": "diem-thi-thpt"
    },
    {
      "id": 134723,
      "school_id": 353,
      "code": "7340120",
      "display_code": null,
      "name": "Kinh doanh quốc tế",
      "block": "A00;A01;D01;D90",
      "mark": 26.5,
      "quota": null,
      "type": 1,
      "mark_type": 1,
      "year": 2023,
      "introtext": "",
      "created_at": "2025-01-01T00:28:01.000Z",
      "updated_at": "2025-01-01T00:28:01.000Z",
      "published_at": null,
      "create_by": "cucnt",
      "status_mark": 1,
      "block_code": null,
      "school_code": null,
      "formula": null,
      "active": null,
      "updated_by": null,
      "admission_name": "Điểm thi THPT",
      "admission_alias": "diem-thi-thpt"
    },
    {
      "id": 134724,
      "school_id": 353,
      "code": "7340121",
      "display_code": null,
      "name": "Kinh doanh thương mại",
      "block": "A00;A01;D01;D90",
      "mark": 26,
      "quota": null,
      "type": 1,
      "mark_type": 1,
      "year": 2023,
      "introtext": "",
      "created_at": "2025-01-01T00:28:01.000Z",
      "updated_at": "2025-01-01T00:28:01.000Z",
      "published_at": null,
      "create_by": "cucnt",
      "status_mark": 1,
      "block_code": null,
      "school_code": null,
      "formula": null,
      "active": null,
      "updated_by": null,
      "admission_name": "Điểm thi THPT",
      "admission_alias": "diem-thi-thpt"
    },
    {
      "id": 134725,
      "school_id": 353,
      "code": "7340122",
      "display_code": null,
      "name": "Thương mại điện tử",
      "block": "A00;A01;D01;D90",
      "mark": 26.5,
      "quota": null,
      "type": 1,
      "mark_type": 1,
      "year": 2023,
      "introtext": "",
      "created_at": "2025-01-01T00:28:01.000Z",
      "updated_at": "2025-01-01T00:28:01.000Z",
      "published_at": null,
      "create_by": "cucnt",
      "status_mark": 1,
      "block_code": null,
      "school_code": null,
      "formula": null,
      "active": null,
      "updated_by": null,
      "admission_name": "Điểm thi THPT",
      "admission_alias": "diem-thi-thpt"
    },
    {
      "id": 134726,
      "school_id": 353,
      "code": "7340201",
      "display_code": null,
      "name": "Tài chính - Ngân hàng",
      "block": "A00;A01;D01;D90",
      "mark": 24,
      "quota": null,
      "type": 1,
      "mark_type": 1,
      "year": 2023,
      "introtext": "",
      "created_at": "2025-01-01T00:28:01.000Z",
      "updated_at": "2025-01-01T00:28:01.000Z",
      "published_at": null,
      "create_by": "cucnt",
      "status_mark": 1,
      "block_code": null,
      "school_code": null,
      "formula": null,
      "active": null,
      "updated_by": null,
      "admission_name": "Điểm thi THPT",
      "admission_alias": "diem-thi-thpt"
    },
    {
      "id": 134736,
      "school_id": 353,
      "code": "7340205",
      "display_code": null,
      "name": "Công nghệ tài chính",
      "block": "A00;A01;D01;D90",
      "mark": 24.25,
      "quota": null,
      "type": 1,
      "mark_type": 1,
      "year": 2023,
      "introtext": "",
      "created_at": "2025-01-01T00:28:01.000Z",
      "updated_at": "2025-01-01T00:28:01.000Z",
      "published_at": null,
      "create_by": "cucnt",
      "status_mark": 1,
      "block_code": null,
      "school_code": null,
      "formula": null,
      "active": null,
      "updated_by": null,
      "admission_name": "Điểm thi THPT",
      "admission_alias": "diem-thi-thpt"
    },
    {
      "id": 134727,
      "school_id": 353,
      "code": "7340301",
      "display_code": null,
      "name": "Kế toán",
      "block": "A00;A01;D01;D90",
      "mark": 23.85,
      "quota": null,
      "type": 1,
      "mark_type": 1,
      "year": 2023,
      "introtext": "",
      "created_at": "2025-01-01T00:28:01.000Z",
      "updated_at": "2025-01-01T00:28:01.000Z",
      "published_at": null,
      "create_by": "cucnt",
      "status_mark": 1,
      "block_code": null,
      "school_code": null,
      "formula": null,
      "active": null,
      "updated_by": null,
      "admission_name": "Điểm thi THPT",
      "admission_alias": "diem-thi-thpt"
    },
    {
      "id": 134728,
      "school_id": 353,
      "code": "7340302",
      "display_code": null,
      "name": "Kiểm toán",
      "block": "A00;A01;D01;D90",
      "mark": 24.25,
      "quota": null,
      "type": 1,
      "mark_type": 1,
      "year": 2023,
      "introtext": "",
      "created_at": "2025-01-01T00:28:01.000Z",
      "updated_at": "2025-01-01T00:28:01.000Z",
      "published_at": null,
      "create_by": "cucnt",
      "status_mark": 1,
      "block_code": null,
      "school_code": null,
      "formula": null,
      "active": null,
      "updated_by": null,
      "admission_name": "Điểm thi THPT",
      "admission_alias": "diem-thi-thpt"
    },
    {
      "id": 134729,
      "school_id": 353,
      "code": "7340404",
      "display_code": null,
      "name": "Quản trị nhân lực",
      "block": "A00;A01;D01;D90",
      "mark": 24.75,
      "quota": null,
      "type": 1,
      "mark_type": 1,
      "year": 2023,
      "introtext": "",
      "created_at": "2025-01-01T00:28:01.000Z",
      "updated_at": "2025-01-01T00:28:01.000Z",
      "published_at": null,
      "create_by": "cucnt",
      "status_mark": 1,
      "block_code": null,
      "school_code": null,
      "formula": null,
      "active": null,
      "updated_by": null,
      "admission_name": "Điểm thi THPT",
      "admission_alias": "diem-thi-thpt"
    },
    {
      "id": 134730,
      "school_id": 353,
      "code": "7340405",
      "display_code": null,
      "name": "Hệ thống thông tin quản lý",
      "block": "A00;A01;D01;D90",
      "mark": 23.75,
      "quota": null,
      "type": 1,
      "mark_type": 1,
      "year": 2023,
      "introtext": "",
      "created_at": "2025-01-01T00:28:01.000Z",
      "updated_at": "2025-01-01T00:28:01.000Z",
      "published_at": null,
      "create_by": "cucnt",
      "status_mark": 1,
      "block_code": null,
      "school_code": null,
      "formula": null,
      "active": null,
      "updated_by": null,
      "admission_name": "Điểm thi THPT",
      "admission_alias": "diem-thi-thpt"
    },
    {
      "id": 134731,
      "school_id": 353,
      "code": "7340420",
      "display_code": null,
      "name": "Khoa học dữ liệu",
      "block": "A00;A01;D01;D90",
      "mark": 24.6,
      "quota": null,
      "type": 1,
      "mark_type": 1,
      "year": 2023,
      "introtext": "",
      "created_at": "2025-01-01T00:28:01.000Z",
      "updated_at": "2025-01-01T00:28:01.000Z",
      "published_at": null,
      "create_by": "cucnt",
      "status_mark": 1,
      "block_code": null,
      "school_code": null,
      "formula": null,
      "active": null,
      "updated_by": null,
      "admission_name": "Điểm thi THPT",
      "admission_alias": "diem-thi-thpt"
    },
    {
      "id": 134732,
      "school_id": 353,
      "code": "7380101",
      "display_code": null,
      "name": "Luật",
      "block": "A00;A01;D01;D96",
      "mark": 23.5,
      "quota": null,
      "type": 1,
      "mark_type": 1,
      "year": 2023,
      "introtext": "",
      "created_at": "2025-01-01T00:28:01.000Z",
      "updated_at": "2025-01-01T00:28:01.000Z",
      "published_at": null,
      "create_by": "cucnt",
      "status_mark": 1,
      "block_code": null,
      "school_code": null,
      "formula": null,
      "active": null,
      "updated_by": null,
      "admission_name": "Điểm thi THPT",
      "admission_alias": "diem-thi-thpt"
    },
    {
      "id": 134733,
      "school_id": 353,
      "code": "7380107",
      "display_code": null,
      "name": "Luật kinh tế",
      "block": "A00;A01;D01;D96",
      "mark": 25.25,
      "quota": null,
      "type": 1,
      "mark_type": 1,
      "year": 2023,
      "introtext": "",
      "created_at": "2025-01-01T00:28:01.000Z",
      "updated_at": "2025-01-01T00:28:01.000Z",
      "published_at": null,
      "create_by": "cucnt",
      "status_mark": 1,
      "block_code": null,
      "school_code": null,
      "formula": null,
      "active": null,
      "updated_by": null,
      "admission_name": "Điểm thi THPT",
      "admission_alias": "diem-thi-thpt"
    },
    {
      "id": 134734,
      "school_id": 353,
      "code": "7810103",
      "display_code": null,
      "name": "Quản trị dịch vụ du lịch và lữ hành",
      "block": "A00;A01;D01;D90",
      "mark": 24.5,
      "quota": null,
      "type": 1,
      "mark_type": 1,
      "year": 2023,
      "introtext": "",
      "created_at": "2025-01-01T00:28:01.000Z",
      "updated_at": "2025-01-01T00:28:01.000Z",
      "published_at": null,
      "create_by": "cucnt",
      "status_mark": 1,
      "block_code": null,
      "school_code": null,
      "formula": null,
      "active": null,
      "updated_by": null,
      "admission_name": "Điểm thi THPT",
      "admission_alias": "diem-thi-thpt"
    },
    {
      "id": 134735,
      "school_id": 353,
      "code": "7810201",
      "display_code": null,
      "name": "Quản trị khách sạn",
      "block": "A00;A01;D01;D90",
      "mark": 23.5,
      "quota": null,
      "type": 1,
      "mark_type": 1,
      "year": 2023,
      "introtext": "",
      "created_at": "2025-01-01T00:28:01.000Z",
      "updated_at": "2025-01-01T00:28:01.000Z",
      "published_at": null,
      "create_by": "cucnt",
      "status_mark": 1,
      "block_code": null,
      "school_code": null,
      "formula": null,
      "active": null,
      "updated_by": null,
      "admission_name": "Điểm thi THPT",
      "admission_alias": "diem-thi-thpt"
    }
  ],
  "msg": ""
}