{
  "success": true,
  "data": [
    {
      "id": 114223,
      "school_id": 221,
      "code": "7480202",
      "display_code": null,
      "name": "An toàn thông tin",
      "block": "A00",
      "mark": 21.84,
      "quota": null,
      "type": 1,
      "mark_type": 1,
      "year": 2022,
      "introtext": "Điểm trúng tuyển nam, Phía bắc",
      "created_at": "2025-01-01T00:28:01.000Z",
      "updated_at": "2025-01-01T00:28:01.000Z",
      "published_at": null,
      "create_by": "cucnt",
      "status_mark": 1,
      "block_code": null,
      "school_code": null,
      "formula": null,
      "active": null,
      "updated_by": null,
      "admission_name": "Điểm thi THPT",
      "admission_alias": "diem-thi-thpt"
    },
    {
      "id": 114224,
      "school_id": 221,
      "code": "7480202",
      "display_code": null,
      "name": "An toàn thông tin",
      "block": "A01",
      "mark": 17.94,
      "quota": null,
      "type": 1,
      "mark_type": 1,
      "year": 2022,
      "introtext": "Điểm trúng tuyển nam, Phía bắc",
      "created_at": "2025-01-01T00:28:01.000Z",
      "updated_at": "2025-01-01T00:28:01.000Z",
      "published_at": null,
      "create_by": "cucnt",
      "status_mark": 1,
      "block_code": null,
      "school_code": null,
      "formula": null,
      "active": null,
      "updated_by": null,
      "admission_name": "Điểm thi THPT",
      "admission_alias": "diem-thi-thpt"
    },
    {
      "id": 114225,
      "school_id": 221,
      "code": "7480202",
      "display_code": null,
      "name": "An toàn thông tin",
      "block": "A00",
      "mark": 21.85,
      "quota": null,
      "type": 1,
      "mark_type": 1,
      "year": 2022,
      "introtext": "Điểm trúng tuyển nữ, Phía bắc",
      "created_at": "2025-01-01T00:28:01.000Z",
      "updated_at": "2025-01-01T00:28:01.000Z",
      "published_at": null,
      "create_by": "cucnt",
      "status_mark": 1,
      "block_code": null,
      "school_code": null,
      "formula": null,
      "active": null,
      "updated_by": null,
      "admission_name": "Điểm thi THPT",
      "admission_alias": "diem-thi-thpt"
    },
    {
      "id": 114226,
      "school_id": 221,
      "code": "7480202",
      "display_code": null,
      "name": "An toàn thông tin",
      "block": "A01",
      "mark": 23.26,
      "quota": null,
      "type": 1,
      "mark_type": 1,
      "year": 2022,
      "introtext": "Điểm trúng tuyển nữ, Phía bắc",
      "created_at": "2025-01-01T00:28:01.000Z",
      "updated_at": "2025-01-01T00:28:01.000Z",
      "published_at": null,
      "create_by": "cucnt",
      "status_mark": 1,
      "block_code": null,
      "school_code": null,
      "formula": null,
      "active": null,
      "updated_by": null,
      "admission_name": "Điểm thi THPT",
      "admission_alias": "diem-thi-thpt"
    },
    {
      "id": 114227,
      "school_id": 221,
      "code": "7480202",
      "display_code": null,
      "name": "An toàn thông tin",
      "block": "A00",
      "mark": 18.89,
      "quota": null,
      "type": 1,
      "mark_type": 1,
      "year": 2022,
      "introtext": "Điểm trúng tuyển nam; Phía Nam",
      "created_at": "2025-01-01T00:28:01.000Z",
      "updated_at": "2025-01-01T00:28:01.000Z",
      "published_at": null,
      "create_by": "cucnt",
      "status_mark": 1,
      "block_code": null,
      "school_code": null,
      "formula": null,
      "active": null,
      "updated_by": null,
      "admission_name": "Điểm thi THPT",
      "admission_alias": "diem-thi-thpt"
    },
    {
      "id": 114228,
      "school_id": 221,
      "code": "7480202",
      "display_code": null,
      "name": "An toàn thông tin",
      "block": "A01",
      "mark": 17.67,
      "quota": null,
      "type": 1,
      "mark_type": 1,
      "year": 2022,
      "introtext": "Điểm trúng tuyển nam; Phía Nam",
      "created_at": "2025-01-01T00:28:01.000Z",
      "updated_at": "2025-01-01T00:28:01.000Z",
      "published_at": null,
      "create_by": "cucnt",
      "status_mark": 1,
      "block_code": null,
      "school_code": null,
      "formula": null,
      "active": null,
      "updated_by": null,
      "admission_name": "Điểm thi THPT",
      "admission_alias": "diem-thi-thpt"
    },
    {
      "id": 114229,
      "school_id": 221,
      "code": "7480202",
      "display_code": null,
      "name": "An toàn thông tin",
      "block": "A00",
      "mark": 21.22,
      "quota": null,
      "type": 1,
      "mark_type": 1,
      "year": 2022,
      "introtext": "Điểm trúng tuyển nữ; Phía Nam",
      "created_at": "2025-01-01T00:28:01.000Z",
      "updated_at": "2025-01-01T00:28:01.000Z",
      "published_at": null,
      "create_by": "cucnt",
      "status_mark": 1,
      "block_code": null,
      "school_code": null,
      "formula": null,
      "active": null,
      "updated_by": null,
      "admission_name": "Điểm thi THPT",
      "admission_alias": "diem-thi-thpt"
    },
    {
      "id": 114230,
      "school_id": 221,
      "code": "7480202",
      "display_code": null,
      "name": "An toàn thông tin",
      "block": "A01",
      "mark": 22,
      "quota": null,
      "type": 1,
      "mark_type": 1,
      "year": 2022,
      "introtext": "Điểm trúng tuyển nữ; Phía Nam",
      "created_at": "2025-01-01T00:28:01.000Z",
      "updated_at": "2025-01-01T00:28:01.000Z",
      "published_at": null,
      "create_by": "cucnt",
      "status_mark": 1,
      "block_code": null,
      "school_code": null,
      "formula": null,
      "active": null,
      "updated_by": null,
      "admission_name": "Điểm thi THPT",
      "admission_alias": "diem-thi-thpt"
    },
    {
      "id": 114232,
      "school_id": 221,
      "code": "7720101",
      "display_code": null,
      "name": "Y khoa",
      "block": "B00",
      "mark": 15.1,
      "quota": null,
      "type": 1,
      "mark_type": 1,
      "year": 2022,
      "introtext": "Điểm trúng tuyển nam; Phía Nam",
      "created_at": "2025-01-01T00:28:01.000Z",
      "updated_at": "2025-01-01T00:28:01.000Z",
      "published_at": null,
      "create_by": "cucnt",
      "status_mark": 1,
      "block_code": null,
      "school_code": null,
      "formula": null,
      "active": null,
      "updated_by": null,
      "admission_name": "Điểm thi THPT",
      "admission_alias": "diem-thi-thpt"
    },
    {
      "id": 114231,
      "school_id": 221,
      "code": "7720101",
      "display_code": null,
      "name": "Y khoa",
      "block": "B00",
      "mark": 15.64,
      "quota": null,
      "type": 1,
      "mark_type": 1,
      "year": 2022,
      "introtext": "Điểm trúng tuyển nam; Phía Bắc",
      "created_at": "2025-01-01T00:28:01.000Z",
      "updated_at": "2025-01-01T00:28:01.000Z",
      "published_at": null,
      "create_by": "cucnt",
      "status_mark": 1,
      "block_code": null,
      "school_code": null,
      "formula": null,
      "active": null,
      "updated_by": null,
      "admission_name": "Điểm thi THPT",
      "admission_alias": "diem-thi-thpt"
    },
    {
      "id": 114207,
      "school_id": 221,
      "code": "7860100",
      "display_code": null,
      "name": "Nghiệp vụ An ninh",
      "block": "A00",
      "mark": 24.69,
      "quota": null,
      "type": 1,
      "mark_type": 1,
      "year": 2022,
      "introtext": "Điểm trúng tuyển nữ; Địa bàn 2",
      "created_at": "2025-01-01T00:28:01.000Z",
      "updated_at": "2025-01-01T00:28:01.000Z",
      "published_at": null,
      "create_by": "cucnt",
      "status_mark": 1,
      "block_code": null,
      "school_code": null,
      "formula": null,
      "active": null,
      "updated_by": null,
      "admission_name": "Điểm thi THPT",
      "admission_alias": "diem-thi-thpt"
    },
    {
      "id": 114221,
      "school_id": 221,
      "code": "7860100",
      "display_code": null,
      "name": "Nghiệp vụ An ninh",
      "block": "C03",
      "mark": 20.24,
      "quota": null,
      "type": 1,
      "mark_type": 1,
      "year": 2022,
      "introtext": "Điểm trúng tuyển nam; Địa bàn 8",
      "created_at": "2025-01-01T00:28:01.000Z",
      "updated_at": "2025-01-01T00:28:01.000Z",
      "published_at": null,
      "create_by": "cucnt",
      "status_mark": 1,
      "block_code": null,
      "school_code": null,
      "formula": null,
      "active": null,
      "updated_by": null,
      "admission_name": "Điểm thi THPT",
      "admission_alias": "diem-thi-thpt"
    },
    {
      "id": 114197,
      "school_id": 221,
      "code": "7860100",
      "display_code": null,
      "name": "Nghiệp vụ An ninh",
      "block": "C03",
      "mark": 20.53,
      "quota": null,
      "type": 1,
      "mark_type": 1,
      "year": 2022,
      "introtext": "Điểm trúng tuyển nam; Địa bàn 1",
      "created_at": "2025-01-01T00:28:01.000Z",
      "updated_at": "2025-01-01T00:28:01.000Z",
      "published_at": null,
      "create_by": "cucnt",
      "status_mark": 1,
      "block_code": null,
      "school_code": null,
      "formula": null,
      "active": null,
      "updated_by": null,
      "admission_name": "Điểm thi THPT",
      "admission_alias": "diem-thi-thpt"
    },
    {
      "id": 114214,
      "school_id": 221,
      "code": "7860100",
      "display_code": null,
      "name": "Nghiệp vụ An ninh",
      "block": "D01",
      "mark": 20.96,
      "quota": null,
      "type": 1,
      "mark_type": 1,
      "year": 2022,
      "introtext": "Điểm trúng tuyển nam; Địa bàn 3",
      "created_at": "2025-01-01T00:28:01.000Z",
      "updated_at": "2025-01-01T00:28:01.000Z",
      "published_at": null,
      "create_by": "cucnt",
      "status_mark": 1,
      "block_code": null,
      "school_code": null,
      "formula": null,
      "active": null,
      "updated_by": null,
      "admission_name": "Điểm thi THPT",
      "admission_alias": "diem-thi-thpt"
    },
    {
      "id": 114222,
      "school_id": 221,
      "code": "7860100",
      "display_code": null,
      "name": "Nghiệp vụ An ninh",
      "block": "D01",
      "mark": 18.3,
      "quota": null,
      "type": 1,
      "mark_type": 1,
      "year": 2022,
      "introtext": "Điểm trúng tuyển nam; Địa bàn 8",
      "created_at": "2025-01-01T00:28:01.000Z",
      "updated_at": "2025-01-01T00:28:01.000Z",
      "published_at": null,
      "create_by": "cucnt",
      "status_mark": 1,
      "block_code": null,
      "school_code": null,
      "formula": null,
      "active": null,
      "updated_by": null,
      "admission_name": "Điểm thi THPT",
      "admission_alias": "diem-thi-thpt"
    },
    {
      "id": 114198,
      "school_id": 221,
      "code": "7860100",
      "display_code": null,
      "name": "Nghiệp vụ An ninh",
      "block": "D01",
      "mark": 20.33,
      "quota": null,
      "type": 1,
      "mark_type": 1,
      "year": 2022,
      "introtext": "Điểm trúng tuyển nam; Địa bàn 1",
      "created_at": "2025-01-01T00:28:01.000Z",
      "updated_at": "2025-01-01T00:28:01.000Z",
      "published_at": null,
      "create_by": "cucnt",
      "status_mark": 1,
      "block_code": null,
      "school_code": null,
      "formula": null,
      "active": null,
      "updated_by": null,
      "admission_name": "Điểm thi THPT",
      "admission_alias": "diem-thi-thpt"
    },
    {
      "id": 114215,
      "school_id": 221,
      "code": "7860100",
      "display_code": null,
      "name": "Nghiệp vụ An ninh",
      "block": "A00",
      "mark": 22.13,
      "quota": null,
      "type": 1,
      "mark_type": 1,
      "year": 2022,
      "introtext": "Điểm trúng tuyển nữ; Địa bàn 3",
      "created_at": "2025-01-01T00:28:01.000Z",
      "updated_at": "2025-01-01T00:28:01.000Z",
      "published_at": null,
      "create_by": "cucnt",
      "status_mark": 1,
      "block_code": null,
      "school_code": null,
      "formula": null,
      "active": null,
      "updated_by": null,
      "admission_name": "Điểm thi THPT",
      "admission_alias": "diem-thi-thpt"
    },
    {
      "id": 114199,
      "school_id": 221,
      "code": "7860100",
      "display_code": null,
      "name": "Nghiệp vụ An ninh",
      "block": "A00",
      "mark": 23.88,
      "quota": null,
      "type": 1,
      "mark_type": 1,
      "year": 2022,
      "introtext": "Điểm trúng tuyển nữ; Địa bàn 1",
      "created_at": "2025-01-01T00:28:01.000Z",
      "updated_at": "2025-01-01T00:28:01.000Z",
      "published_at": null,
      "create_by": "cucnt",
      "status_mark": 1,
      "block_code": null,
      "school_code": null,
      "formula": null,
      "active": null,
      "updated_by": null,
      "admission_name": "Điểm thi THPT",
      "admission_alias": "diem-thi-thpt"
    },
    {
      "id": 114216,
      "school_id": 221,
      "code": "7860100",
      "display_code": null,
      "name": "Nghiệp vụ An ninh",
      "block": "A01",
      "mark": 24.94,
      "quota": null,
      "type": 1,
      "mark_type": 1,
      "year": 2022,
      "introtext": "Điểm trúng tuyển nữ; Địa bàn 3",
      "created_at": "2025-01-01T00:28:01.000Z",
      "updated_at": "2025-01-01T00:28:01.000Z",
      "published_at": null,
      "create_by": "cucnt",
      "status_mark": 1,
      "block_code": null,
      "school_code": null,
      "formula": null,
      "active": null,
      "updated_by": null,
      "admission_name": "Điểm thi THPT",
      "admission_alias": "diem-thi-thpt"
    },
    {
      "id": 114200,
      "school_id": 221,
      "code": "7860100",
      "display_code": null,
      "name": "Nghiệp vụ An ninh",
      "block": "A01",
      "mark": 25.66,
      "quota": null,
      "type": 1,
      "mark_type": 1,
      "year": 2022,
      "introtext": "Điểm trúng tuyển nữ; Địa bàn 1",
      "created_at": "2025-01-01T00:28:01.000Z",
      "updated_at": "2025-01-01T00:28:01.000Z",
      "published_at": null,
      "create_by": "cucnt",
      "status_mark": 1,
      "block_code": null,
      "school_code": null,
      "formula": null,
      "active": null,
      "updated_by": null,
      "admission_name": "Điểm thi THPT",
      "admission_alias": "diem-thi-thpt"
    },
    {
      "id": 114217,
      "school_id": 221,
      "code": "7860100",
      "display_code": null,
      "name": "Nghiệp vụ An ninh",
      "block": "C03",
      "mark": 25.3,
      "quota": null,
      "type": 1,
      "mark_type": 1,
      "year": 2022,
      "introtext": "Điểm trúng tuyển nữ; Địa bàn 3",
      "created_at": "2025-01-01T00:28:01.000Z",
      "updated_at": "2025-01-01T00:28:01.000Z",
      "published_at": null,
      "create_by": "cucnt",
      "status_mark": 1,
      "block_code": null,
      "school_code": null,
      "formula": null,
      "active": null,
      "updated_by": null,
      "admission_name": "Điểm thi THPT",
      "admission_alias": "diem-thi-thpt"
    },
    {
      "id": 114218,
      "school_id": 221,
      "code": "7860100",
      "display_code": null,
      "name": "Nghiệp vụ An ninh",
      "block": "D01",
      "mark": 24.64,
      "quota": null,
      "type": 1,
      "mark_type": 1,
      "year": 2022,
      "introtext": "Điểm trúng tuyển nữ; Địa bàn 3",
      "created_at": "2025-01-01T00:28:01.000Z",
      "updated_at": "2025-01-01T00:28:01.000Z",
      "published_at": null,
      "create_by": "cucnt",
      "status_mark": 1,
      "block_code": null,
      "school_code": null,
      "formula": null,
      "active": null,
      "updated_by": null,
      "admission_name": "Điểm thi THPT",
      "admission_alias": "diem-thi-thpt"
    },
    {
      "id": 114201,
      "school_id": 221,
      "code": "7860100",
      "display_code": null,
      "name": "Nghiệp vụ An ninh",
      "block": "C03",
      "mark": 24.92,
      "quota": null,
      "type": 1,
      "mark_type": 1,
      "year": 2022,
      "introtext": "Điểm trúng tuyển nữ; Địa bàn 1",
      "created_at": "2025-01-01T00:28:01.000Z",
      "updated_at": "2025-01-01T00:28:01.000Z",
      "published_at": null,
      "create_by": "cucnt",
      "status_mark": 1,
      "block_code": null,
      "school_code": null,
      "formula": null,
      "active": null,
      "updated_by": null,
      "admission_name": "Điểm thi THPT",
      "admission_alias": "diem-thi-thpt"
    },
    {
      "id": 114208,
      "school_id": 221,
      "code": "7860100",
      "display_code": null,
      "name": "Nghiệp vụ An ninh",
      "block": "A01",
      "mark": 23.16,
      "quota": null,
      "type": 1,
      "mark_type": 1,
      "year": 2022,
      "introtext": "Điểm trúng tuyển nữ; Địa bàn 2",
      "created_at": "2025-01-01T00:28:01.000Z",
      "updated_at": "2025-01-01T00:28:01.000Z",
      "published_at": null,
      "create_by": "cucnt",
      "status_mark": 1,
      "block_code": null,
      "school_code": null,
      "formula": null,
      "active": null,
      "updated_by": null,
      "admission_name": "Điểm thi THPT",
      "admission_alias": "diem-thi-thpt"
    },
    {
      "id": 114202,
      "school_id": 221,
      "code": "7860100",
      "display_code": null,
      "name": "Nghiệp vụ An ninh",
      "block": "D01",
      "mark": 25.3,
      "quota": null,
      "type": 1,
      "mark_type": 1,
      "year": 2022,
      "introtext": "Điểm trúng tuyển nữ; Địa bàn 1",
      "created_at": "2025-01-01T00:28:01.000Z",
      "updated_at": "2025-01-01T00:28:01.000Z",
      "published_at": null,
      "create_by": "cucnt",
      "status_mark": 1,
      "block_code": null,
      "school_code": null,
      "formula": null,
      "active": null,
      "updated_by": null,
      "admission_name": "Điểm thi THPT",
      "admission_alias": "diem-thi-thpt"
    },
    {
      "id": 114219,
      "school_id": 221,
      "code": "7860100",
      "display_code": null,
      "name": "Nghiệp vụ An ninh",
      "block": "A00",
      "mark": 19.12,
      "quota": null,
      "type": 1,
      "mark_type": 1,
      "year": 2022,
      "introtext": "Điểm trúng tuyển nam; Địa bàn 8",
      "created_at": "2025-01-01T00:28:01.000Z",
      "updated_at": "2025-01-01T00:28:01.000Z",
      "published_at": null,
      "create_by": "cucnt",
      "status_mark": 1,
      "block_code": null,
      "school_code": null,
      "formula": null,
      "active": null,
      "updated_by": null,
      "admission_name": "Điểm thi THPT",
      "admission_alias": "diem-thi-thpt"
    },
    {
      "id": 114209,
      "school_id": 221,
      "code": "7860100",
      "display_code": null,
      "name": "Nghiệp vụ An ninh",
      "block": "C03",
      "mark": 24.56,
      "quota": null,
      "type": 1,
      "mark_type": 1,
      "year": 2022,
      "introtext": "Điểm trúng tuyển nữ; Địa bàn 2",
      "created_at": "2025-01-01T00:28:01.000Z",
      "updated_at": "2025-01-01T00:28:01.000Z",
      "published_at": null,
      "create_by": "cucnt",
      "status_mark": 1,
      "block_code": null,
      "school_code": null,
      "formula": null,
      "active": null,
      "updated_by": null,
      "admission_name": "Điểm thi THPT",
      "admission_alias": "diem-thi-thpt"
    },
    {
      "id": 114203,
      "school_id": 221,
      "code": "7860100",
      "display_code": null,
      "name": "Nghiệp vụ An ninh",
      "block": "A00",
      "mark": 21.61,
      "quota": null,
      "type": 1,
      "mark_type": 1,
      "year": 2022,
      "introtext": "Điểm trúng tuyển nam; Địa bàn 2; Tiêu chí phụ: Thí sinh có tổng điểm của 03 môn thuộc tổ hợp xét tuyển (chiếm tỷ lệ 40%) và điểm bài thi Bộ Công an (chiếm tỷ lệ 60%) được quy về thang điểm 30 làm tròn đến 02 chữ số thập phân (không tính điểm ưu tiên, điểm thưởng) đạt 21.11đ",
      "created_at": "2025-01-01T00:28:01.000Z",
      "updated_at": "2025-01-01T00:28:01.000Z",
      "published_at": null,
      "create_by": "cucnt",
      "status_mark": 1,
      "block_code": null,
      "school_code": null,
      "formula": null,
      "active": null,
      "updated_by": null,
      "admission_name": "Điểm thi THPT",
      "admission_alias": "diem-thi-thpt"
    },
    {
      "id": 114220,
      "school_id": 221,
      "code": "7860100",
      "display_code": null,
      "name": "Nghiệp vụ An ninh",
      "block": "A01",
      "mark": 19.47,
      "quota": null,
      "type": 1,
      "mark_type": 1,
      "year": 2022,
      "introtext": "Điểm trúng tuyển nam; Địa bàn 8",
      "created_at": "2025-01-01T00:28:01.000Z",
      "updated_at": "2025-01-01T00:28:01.000Z",
      "published_at": null,
      "create_by": "cucnt",
      "status_mark": 1,
      "block_code": null,
      "school_code": null,
      "formula": null,
      "active": null,
      "updated_by": null,
      "admission_name": "Điểm thi THPT",
      "admission_alias": "diem-thi-thpt"
    },
    {
      "id": 114210,
      "school_id": 221,
      "code": "7860100",
      "display_code": null,
      "name": "Nghiệp vụ An ninh",
      "block": "D01",
      "mark": 22.44,
      "quota": null,
      "type": 1,
      "mark_type": 1,
      "year": 2022,
      "introtext": "Điểm trúng tuyển nữ; Địa bàn 2",
      "created_at": "2025-01-01T00:28:01.000Z",
      "updated_at": "2025-01-01T00:28:01.000Z",
      "published_at": null,
      "create_by": "cucnt",
      "status_mark": 1,
      "block_code": null,
      "school_code": null,
      "formula": null,
      "active": null,
      "updated_by": null,
      "admission_name": "Điểm thi THPT",
      "admission_alias": "diem-thi-thpt"
    },
    {
      "id": 114204,
      "school_id": 221,
      "code": "7860100",
      "display_code": null,
      "name": "Nghiệp vụ An ninh",
      "block": "A01",
      "mark": 22.39,
      "quota": null,
      "type": 1,
      "mark_type": 1,
      "year": 2022,
      "introtext": "Điểm trúng tuyển nam; Địa bàn 2",
      "created_at": "2025-01-01T00:28:01.000Z",
      "updated_at": "2025-01-01T00:28:01.000Z",
      "published_at": null,
      "create_by": "cucnt",
      "status_mark": 1,
      "block_code": null,
      "school_code": null,
      "formula": null,
      "active": null,
      "updated_by": null,
      "admission_name": "Điểm thi THPT",
      "admission_alias": "diem-thi-thpt"
    },
    {
      "id": 114211,
      "school_id": 221,
      "code": "7860100",
      "display_code": null,
      "name": "Nghiệp vụ An ninh",
      "block": "A00",
      "mark": 20.06,
      "quota": null,
      "type": 1,
      "mark_type": 1,
      "year": 2022,
      "introtext": "Điểm trúng tuyển nam; Địa bàn 3",
      "created_at": "2025-01-01T00:28:01.000Z",
      "updated_at": "2025-01-01T00:28:01.000Z",
      "published_at": null,
      "create_by": "cucnt",
      "status_mark": 1,
      "block_code": null,
      "school_code": null,
      "formula": null,
      "active": null,
      "updated_by": null,
      "admission_name": "Điểm thi THPT",
      "admission_alias": "diem-thi-thpt"
    },
    {
      "id": 114205,
      "school_id": 221,
      "code": "7860100",
      "display_code": null,
      "name": "Nghiệp vụ An ninh",
      "block": "C03",
      "mark": 21.84,
      "quota": null,
      "type": 1,
      "mark_type": 1,
      "year": 2022,
      "introtext": "Điểm trúng tuyển nam; Địa bàn 2",
      "created_at": "2025-01-01T00:28:01.000Z",
      "updated_at": "2025-01-01T00:28:01.000Z",
      "published_at": null,
      "create_by": "cucnt",
      "status_mark": 1,
      "block_code": null,
      "school_code": null,
      "formula": null,
      "active": null,
      "updated_by": null,
      "admission_name": "Điểm thi THPT",
      "admission_alias": "diem-thi-thpt"
    },
    {
      "id": 114212,
      "school_id": 221,
      "code": "7860100",
      "display_code": null,
      "name": "Nghiệp vụ An ninh",
      "block": "A01",
      "mark": 20.92,
      "quota": null,
      "type": 1,
      "mark_type": 1,
      "year": 2022,
      "introtext": "Điểm trúng tuyển nam; Địa bàn 3",
      "created_at": "2025-01-01T00:28:01.000Z",
      "updated_at": "2025-01-01T00:28:01.000Z",
      "published_at": null,
      "create_by": "cucnt",
      "status_mark": 1,
      "block_code": null,
      "school_code": null,
      "formula": null,
      "active": null,
      "updated_by": null,
      "admission_name": "Điểm thi THPT",
      "admission_alias": "diem-thi-thpt"
    },
    {
      "id": 114195,
      "school_id": 221,
      "code": "7860100",
      "display_code": null,
      "name": "Nghiệp vụ An ninh",
      "block": "A00",
      "mark": 19.03,
      "quota": null,
      "type": 1,
      "mark_type": 1,
      "year": 2022,
      "introtext": "Điểm trúng tuyển nam; Địa bàn 1",
      "created_at": "2025-01-01T00:28:01.000Z",
      "updated_at": "2025-01-01T00:28:01.000Z",
      "published_at": null,
      "create_by": "cucnt",
      "status_mark": 1,
      "block_code": null,
      "school_code": null,
      "formula": null,
      "active": null,
      "updated_by": null,
      "admission_name": "Điểm thi THPT",
      "admission_alias": "diem-thi-thpt"
    },
    {
      "id": 114206,
      "school_id": 221,
      "code": "7860100",
      "display_code": null,
      "name": "Nghiệp vụ An ninh",
      "block": "D01",
      "mark": 21.89,
      "quota": null,
      "type": 1,
      "mark_type": 1,
      "year": 2022,
      "introtext": "Điểm trúng tuyển nam; Địa bàn 2",
      "created_at": "2025-01-01T00:28:01.000Z",
      "updated_at": "2025-01-01T00:28:01.000Z",
      "published_at": null,
      "create_by": "cucnt",
      "status_mark": 1,
      "block_code": null,
      "school_code": null,
      "formula": null,
      "active": null,
      "updated_by": null,
      "admission_name": "Điểm thi THPT",
      "admission_alias": "diem-thi-thpt"
    },
    {
      "id": 114196,
      "school_id": 221,
      "code": "7860100",
      "display_code": null,
      "name": "Nghiệp vụ An ninh",
      "block": "A01",
      "mark": 19.62,
      "quota": null,
      "type": 1,
      "mark_type": 1,
      "year": 2022,
      "introtext": "Điểm trúng tuyển nam; Địa bàn 1",
      "created_at": "2025-01-01T00:28:01.000Z",
      "updated_at": "2025-01-01T00:28:01.000Z",
      "published_at": null,
      "create_by": "cucnt",
      "status_mark": 1,
      "block_code": null,
      "school_code": null,
      "formula": null,
      "active": null,
      "updated_by": null,
      "admission_name": "Điểm thi THPT",
      "admission_alias": "diem-thi-thpt"
    },
    {
      "id": 114213,
      "school_id": 221,
      "code": "7860100",
      "display_code": null,
      "name": "Nghiệp vụ An ninh",
      "block": "C03",
      "mark": 21.63,
      "quota": null,
      "type": 1,
      "mark_type": 1,
      "year": 2022,
      "introtext": "Điểm trúng tuyển nam; Địa bàn 3",
      "created_at": "2025-01-01T00:28:01.000Z",
      "updated_at": "2025-01-01T00:28:01.000Z",
      "published_at": null,
      "create_by": "cucnt",
      "status_mark": 1,
      "block_code": null,
      "school_code": null,
      "formula": null,
      "active": null,
      "updated_by": null,
      "admission_name": "Điểm thi THPT",
      "admission_alias": "diem-thi-thpt"
    }
  ],
  "msg": ""
}